fml.py
fml-1.0.1.dist-info/LICENSE
fml-1.0.1.dist-info/METADATA
fml-1.0.1.dist-info/WHEEL
fml-1.0.1.dist-info/entry_points.txt
fml-1.0.1.dist-info/top_level.txt
fml-1.0.1.dist-info/RECORD
