Metadata-Version: 2.1
Name: fml
Version: 1.0.1
Summary: A small CLI app to see a joke on your terminal when you are down.
Home-page: https://github.com/slash-arun/fml/
Author: Arun
Author-email: slash-arun@outlook.com
License: MIT
Platform: UNKNOWN
Classifier: License :: OSI Approved :: MIT License
Classifier: Programming Language :: Python
Classifier: Programming Language :: Python :: 3 :: Only
Classifier: Programming Language :: Python :: 3.6
Classifier: Programming Language :: Python :: 3.7
Classifier: Programming Language :: Python :: Implementation :: CPython
Classifier: Programming Language :: Python :: Implementation :: PyPy
Requires-Python: >=3.6.0
Requires-Dist: requests
Requires-Dist: cowsay
